csvprint/__init__.py
csvprint/parse_types.py
csvprint/parser.py
csvprint/printer.py
csvprint-0.7.1.dist-info/entry_points.txt
csvprint-0.7.1.dist-info/LICENSE
csvprint-0.7.1.dist-info/WHEEL
csvprint-0.7.1.dist-info/METADATA
csvprint-0.7.1.dist-info/RECORD
