Metadata-Version: 2.1
Name: csvprint
Version: 0.7.1
Summary: Print csv files in columnated format, either plain or as a Markdown or LaTeX table
Home-page: https://github.com/vegarsti/csvprint
License: MIT
Keywords: csv
Author: Vegard Stikbakke
Author-email: vegard.stikbakke@gmail.com
Requires-Python: >=3.6,<4.0
Classifier: License :: OSI Approved :: MIT License
Classifier: Programming Language :: Python :: 3
Classifier: Programming Language :: Python :: 3.6
Classifier: Programming Language :: Python :: 3.7
Classifier: Programming Language :: Python :: 3.8
Project-URL: Repository, https://github.com/vegarsti/csvprint
